{"otherData": {}, "traceEvents": [{"cat": "function", "dur": 406862,"name": "sycl::queue __cdecl create_device_queue(void)","ph": "X","pid": 0,"tid": 0,"ts": 284195993371}, {"cat": "function", "dur": 177787091,"name": "void __cdecl MatrixMulParallelNaive(sycl::queue &, size_t, size_t, size_t, float *, float *, float *)","ph": "X","pid": 0,"tid": 0,"ts": 284196400912}, {"cat": "function", "dur": 62007048,"name": "void __cdecl MatrixMulTiled(sycl::queue &, size_t, size_t, size_t, float *, float *, float *)","ph": "X","pid": 0,"tid": 0,"ts": 284374189487}, {"cat": "function", "dur": 61422983,"name": "void __cdecl MatrixMulTiled(sycl::queue &, size_t, size_t, size_t, float *, float *, float *)","ph": "X","pid": 0,"tid": 0,"ts": 284436198158}, {"cat": "function", "dur": 62486316,"name": "void __cdecl MatrixMulTiled(sycl::queue &, size_t, size_t, size_t, float *, float *, float *)","ph": "X","pid": 0,"tid": 0,"ts": 284497622728}, {"cat": "function", "dur": 42258278,"name": "void __cdecl MatrixMulWPT(sycl::queue &, size_t, size_t, size_t, float *, float *, float *)","ph": "X","pid": 0,"tid": 0,"ts": 284560110593}, {"cat": "function", "dur": 42029603,"name": "void __cdecl MatrixMulWPT(sycl::queue &, size_t, size_t, size_t, float *, float *, float *)","ph": "X","pid": 0,"tid": 0,"ts": 284602370599}, {"cat": "function", "dur": 41983984,"name": "void __cdecl MatrixMulWPT(sycl::queue &, size_t, size_t, size_t, float *, float *, float *)","ph": "X","pid": 0,"tid": 0,"ts": 284644402045}, {"cat": "function", "dur": 39896996,"name": "void __cdecl MatrixMulWideWPT(sycl::queue &, size_t, size_t, size_t, float *, float *, float *)","ph": "X","pid": 0,"tid": 0,"ts": 284686388060}, {"cat": "function", "dur": 40261362,"name": "void __cdecl MatrixMulWideWPT(sycl::queue &, size_t, size_t, size_t, float *, float *, float *)","ph": "X","pid": 0,"tid": 0,"ts": 284726294989}, {"cat": "function", "dur": 40006068,"name": "void __cdecl MatrixMulWideWPT(sycl::queue &, size_t, size_t, size_t, float *, float *, float *)","ph": "X","pid": 0,"tid": 0,"ts": 284766558678}, {"cat": "function", "dur": 931634,"name": "static bool __cdecl Verify<float>::VerifyResult(size_t, size_t, T *, T *) [T = float]","ph": "X","pid": 0,"tid": 0,"ts": 284806581724}, {"cat": "function", "dur": 941762,"name": "static bool __cdecl Verify<float>::VerifyResult(size_t, size_t, T *, T *) [T = float]","ph": "X","pid": 0,"tid": 0,"ts": 284807513849}, {"cat": "function", "dur": 910375,"name": "static bool __cdecl Verify<float>::VerifyResult(size_t, size_t, T *, T *) [T = float]","ph": "X","pid": 0,"tid": 0,"ts": 284808456094}, {"cat": "function", "dur": 929807,"name": "static bool __cdecl Verify<float>::VerifyResult(size_t, size_t, T *, T *) [T = float]","ph": "X","pid": 0,"tid": 0,"ts": 284809368221}]}